jupyter_play/__init__.py
jupyter_play/html_games.zip
jupyter_play/py.typed
jupyter_play/html_games/bomberman.html
jupyter_play/html_games/breakout.html
jupyter_play/html_games/doodle-jump.html
jupyter_play/html_games/frogger.html
jupyter_play/html_games/helicopter.html
jupyter_play/html_games/missile-command.html
jupyter_play/html_games/pong.html
jupyter_play/html_games/puzzle-bobble.html
jupyter_play/html_games/snake.html
jupyter_play/html_games/sokoban.html
jupyter_play/html_games/tetris.html
jupyter_play-0.1.0.dist-info/METADATA
jupyter_play-0.1.0.dist-info/WHEEL
jupyter_play-0.1.0.dist-info/top_level.txt
jupyter_play-0.1.0.dist-info/RECORD
