Metadata-Version: 2.1
Name: jupyter-play
Version: 0.1.0
Summary: Play classic games in your Jupyter Notebook! Includes a collection of basic JS/HTML/CSS games from Steven Lambert (Github: straker)
Project-URL: Repository, https://github.com/apsocarras/jupyter-play
Project-URL: Game Sources, https://gist.github.com/straker
Requires-Python: >=3.11
Requires-Dist: ipython>=8.30.0
Requires-Dist: setuptools>=75.6.0
